dasscostorageclient/__init__.py
dasscostorageclient/constants.py
dasscostorageclient/dassco_storage_client.py
dasscostorageclient/utils.py
dasscostorageclient/core/__init__.py
dasscostorageclient/core/enums.py
dasscostorageclient/core/models.py
dasscostorageclient/core/utils.py
dasscostorageclient/exceptions/__init__.py
dasscostorageclient/exceptions/api_error.py
dasscostorageclient/resources/__init__.py
dasscostorageclient/resources/assets.py
dasscostorageclient/resources/collections.py
dasscostorageclient/resources/fileproxy.py
dasscostorageclient/resources/institutions.py
dasscostorageclient/resources/pipelines.py
dasscostorageclient/resources/specimens.py
dasscostorageclient/resources/workstations.py
dasscostorageclient/resources/models/__init__.py
dasscostorageclient/resources/models/external_publisher.py
dasscostorageclient/resources/models/httpinfo.py
dasscostorageclient/resources/models/issues.py
dasscostorageclient/resources/models/legality.py
dasscostorageclient/resources/models/specimen.py
tests/__init__.py
tests/dassco_test_client.py
tests/test_assets.py
tests/test_collections.py
tests/test_fileproxy.py
tests/test_institutions.py
tests/test_pipelines.py
tests/test_specimens.py
tests/test_workstations.py
dasscostorageclient-0.0.13.dist-info/METADATA
dasscostorageclient-0.0.13.dist-info/WHEEL
dasscostorageclient-0.0.13.dist-info/top_level.txt
dasscostorageclient-0.0.13.dist-info/RECORD
